comfy_proxy/__init__.py
comfy_proxy/address.py
comfy_proxy/comfy.py
comfy_proxy/workflow.py
comfy_proxy/workflows/__init__.py
comfy_proxy/workflows/flux.py
comfy_proxy/workflows/qwen_image.py
comfy_proxy/workflows/qwen_image_edit_2509.py
comfy_proxy/workflows/wan_i2v.py
comfy_proxy/workflows/workflow.json
comfy_proxy-0.2.0.dist-info/METADATA
comfy_proxy-0.2.0.dist-info/WHEEL
comfy_proxy-0.2.0.dist-info/licenses/LICENSE
comfy_proxy-0.2.0.dist-info/RECORD
