Metadata-Version: 2.4
Name: comfy-proxy
Version: 0.2.0
Summary: A Python client library for interacting with ComfyUI servers and managing image generation workflows.
License: MIT
License-File: LICENSE
Author: Brian Luczkiewicz
Author-email: brian@blucz.com
Requires-Python: >=3.11,<4.0
Classifier: License :: OSI Approved :: MIT License
Classifier: Programming Language :: Python :: 3
Classifier: Programming Language :: Python :: 3.11
Classifier: Programming Language :: Python :: 3.12
Classifier: Programming Language :: Python :: 3.13
Classifier: Programming Language :: Python :: 3.14
Requires-Dist: aiohttp (>=3.9.1,<4.0.0)
Requires-Dist: pillow (>=10.1.0,<11.0.0)
Requires-Dist: websockets (>=12.0,<13.0)
